setup.py
write_patch/__init__.py
write_patch.egg-info/PKG-INFO
write_patch.egg-info/SOURCES.txt
write_patch.egg-info/dependency_links.txt
write_patch.egg-info/not-zip-safe
write_patch.egg-info/top_level.txt