Metadata-Version: 1.0
Name: write-patch
Version: 0.1
Summary: This is the write patch module for the turtle module, so turtle can write text with angle argument.配合Python海龟画图写字补丁模块，这样就能让海龟写斜着的字了
Home-page: https://github.com/lixingqiu/write_patch
Author: lixingqiu
Author-email: 406273900@qq.com
License: MIT
Platform: UNKNOWN
